dlcliche/__init__.py
dlcliche/big_h5_array.py
dlcliche/data.py
dlcliche/excel.py
dlcliche/fastai.py
dlcliche/general.py
dlcliche/ignore_warnings.py
dlcliche/image.py
dlcliche/math.py
dlcliche/nlp_base.py
dlcliche/nlp_mecab.py
dlcliche/nlp_sudachi.py
dlcliche/notebook.py
dlcliche/projectml.py
dlcliche/pytorch_utils.py
dlcliche/server.py
dlcliche/system.py
dlcliche/test.py
dlcliche/torch_utils.py
dlcliche/utils.py
dlcliche/external/__init__.py
dlcliche/external/smoothing.py
dl_cliche-0.1.12.dist-info/LICENSE
dl_cliche-0.1.12.dist-info/METADATA
dl_cliche-0.1.12.dist-info/WHEEL
dl_cliche-0.1.12.dist-info/top_level.txt
dl_cliche-0.1.12.dist-info/RECORD
