Metadata-Version: 2.1
Name: dl-cliche
Version: 0.1.12
Summary: dl-cliche: Packaging cliche utilities
Home-page: https://github.com/daisukelab/dl-cliche
Author: daisukelab
Author-email: contact.daisukelab@gmail.com
License: Type license() to see the full license text
Platform: UNKNOWN
Classifier: Programming Language :: Python :: 3
Requires-Dist: numpy
Requires-Dist: pandas
Requires-Dist: matplotlib
Requires-Dist: tqdm
Requires-Dist: pyyaml
Requires-Dist: easydict
Requires-Dist: imbalanced-learn
Requires-Dist: tables
Requires-Dist: openpyxl
